asciiartist/__init__.py
asciiartist/gen/_onehot.txt
asciiartist/gen/ascii-model.tflite
asciiartist-0.5.4.dist-info/LICENSE
asciiartist-0.5.4.dist-info/WHEEL
asciiartist-0.5.4.dist-info/METADATA
asciiartist-0.5.4.dist-info/RECORD
