Metadata-Version: 2.1
Name: asciiartist
Version: 0.5.4
Summary: An ascii art generator that's actually good. Does edge detection and selects the most appropriate characters.
Home-page: https://github.com/JuliaPoo/AsciiArtist
License: MIT
Author: Julia
Author-email: julia.poo.poo.poo@gmail.com
Requires-Python: >=3.7,<=3.9
Classifier: License :: OSI Approved :: MIT License
Classifier: Programming Language :: Python :: 3
Classifier: Programming Language :: Python :: 3.7
Classifier: Programming Language :: Python :: 3.8
Classifier: Programming Language :: Python :: 3.9
Requires-Dist: matplotlib
Requires-Dist: scikit-image
Requires-Dist: tflite-runtime
Project-URL: Repository, https://github.com/JuliaPoo/AsciiArtist
